Automatic Door/Automatic Door.v
module Auto_Door(
  input wire UP_Max,
  input wire DN_Max,
  input wire Activate,
  input wire CLK,
  input wire RST,
  
  output reg UP_M,
  output reg DN_M
  
);
  localparam  IDEAL = 2'b00,
              MV_UP = 2'b01,
			  MV_DN = 2'b10;
			  
			  
  reg [1:0] current_state, next_state;

always @(posedge CLK or negedge RST)
  begin
    if(!RST)
	  begin
	   current_state <= IDEAL;
	  end
    else
	  begin
	   current_state <= next_state;
	  end
  end
   
always @(*)
  begin
    case(current_state)
	  IDEAL : begin
	           
			    if(Activate && UP_Max && !DN_Max )
			     begin
				    next_state = MV_DN;
				 end
			    else if(Activate && DN_Max && !UP_Max)
				 begin
				    next_state = MV_UP;
				 end
				else 
				 begin
				    next_state = IDEAL;
				 end
				
		      end
			  
	  MV_UP : begin
               
			    if(UP_Max)
				 begin
				    next_state = IDEAL;
				 end
				else
				 begin
				    next_state = MV_UP;
				 end
              end
			  
	  MV_DN : begin
               
			    if(DN_Max)
				 begin
				    next_state = IDEAL;
				 end
				else
				 begin
				    next_state = MV_DN;
				 end
              end
    default : begin
                    next_state = IDEAL;
	          end
    endcase
  end
always @(*)
 begin
  case(current_state)
  IDEAL     : begin
              UP_M = 1'b0;
			  DN_M = 1'b0;		  
             end
  MV_UP    : begin
              UP_M = 1'b1;
			  DN_M = 1'b0;
             end	
  MV_DN    : begin
              DN_M = 1'b1;
              UP_M = 1'b0;		  
             end
  	
  default  : begin
              UP_M = 1'b0;
			  DN_M = 1'b0;
             end			  
  endcase
  end
  
 
endmodule

Automatic Door/Automatic Door TB.v
`timescale 1ns/1ps

module Auto_Door_TB();

  reg UP_Max_tb;
  reg DN_Max_tb;
  reg Activate_tb;
  reg CLK_tb;
  reg RST_tb;
  
  wire UP_M_tb;
  wire DN_M_tb;

parameter CLK_PERIOD = 20;

always #(CLK_PERIOD/2) CLK_tb = ~CLK_tb;

Auto_Door DUT(
  .UP_Max(UP_Max_tb),
  .DN_Max(DN_Max_tb),
  .Activate(Activate_tb),
  .CLK(CLK_tb),
  .RST(RST_tb),
  .UP_M(UP_M_tb),
  .DN_M(DN_M_tb)
 );
 
initial 
  begin
    $dumpfile("Auto_Door.vcd");
	$dumpvars;
	
	
	initialize();	
	Reset();
	
	Activate_tb = 1'b1; // Test Open Door. 
    #CLK_PERIOD
	Test(Activate_tb,UP_Max_tb,DN_Max_tb);
	
	#(2*CLK_PERIOD)
	UP_Max_tb   = 1'b1;
	DN_Max_tb   = 1'b0;
	Activate_tb = 1'b0; // Test keep Door Open.
	Test(Activate_tb,UP_Max_tb,DN_Max_tb);
	
	#CLK_PERIOD
	Activate_tb = 1'b1; // Test Close Door.
	//UP_Max_tb   = 1'b1;
	//DN_Max_tb   = 1'b0;
	#(CLK_PERIOD)
	Test(Activate_tb,UP_Max_tb,DN_Max_tb);
	
	#(2*CLK_PERIOD)
	Activate_tb = 1'b0; // Test keep Door Closed.
	UP_Max_tb   = 1'b0;
	DN_Max_tb   = 1'b1;
	Test(Activate_tb,UP_Max_tb,DN_Max_tb);
	
	
   #100
   $stop;
  end
  
task initialize;
  begin
    Activate_tb = 1'b0;
	CLK_tb      = 1'b0;
	RST_tb      = 1'b0;
	UP_Max_tb   = 1'b0;
	DN_Max_tb   = 1'b1;
  end
endtask 
  
task Reset;
  begin
    RST_tb =  'b1;
    #CLK_PERIOD
    RST_tb  = 'b0;
    #CLK_PERIOD
    RST_tb  = 'b1;
  end
endtask

task Test;
 input active;
 input sensor_up;
 input sensor_dn;
 
 begin
    
	  
	if(active && sensor_dn )
	  begin
	    if(UP_M_tb==1'b1)
		 $display("Test Open Door is Succeded and UP_M = %b ",UP_M_tb);
		else
		 $display("Test Open Door is Failed and UP_M = %b ",UP_M_tb);
	  end
	else if(active && sensor_up )
	  begin
	    if(DN_M_tb==1'b1)
		 $display("Test Close Door is Succeded and DN_M = %b ",DN_M_tb);
		else
		 $display("Test Close Door is Failed and DN_M = %b ",DN_M_tb);
	  end
	  
	else
	  begin
	      if(sensor_up)
		    begin
		      if(UP_M_tb==1'b1)
		       $display("Test keep Door Open is Succeded and UP_M = %b ",UP_M_tb);
		      else
		       $display("Test keep Door Open is Failed and UP_M = %b ",UP_M_tb);
		    end
			
		  else 
		    begin
		      if(DN_M_tb==1'b1)
		       $display("Test keep Door Closed is Succeded and DN_M = %b ",DN_M_tb);
		      else
		       $display("Test keep Door Closed is Failed and DN_M = %b ",DN_M_tb);
		    end
		  
	  end
 end
endtask
  
  
endmodule

Automatic Door/Auto_Door.vcd
$date
	Thu Mar 07 02:09:27 2024
$end
$version
	ModelSim Version 10.1d
$end
$timescale
	1ps
$end
$scope module Auto_Door_TB $end
$var parameter 32 ! CLK_PERIOD $end
$var reg 1 " UP_Max_tb $end
$var reg 1 # DN_Max_tb $end
$var reg 1 $ Activate_tb $end
$var reg 1 % CLK_tb $end
$var reg 1 & RST_tb $end
$var wire 1 ' UP_M_tb $end
$var wire 1 ( DN_M_tb $end
$scope task initialize $end
$upscope $end
$scope task Reset $end
$upscope $end
$scope task Test $end
$var reg 1 ) active $end
$var reg 1 * sensor_up $end
$var reg 1 + sensor_dn $end
$upscope $end
$scope module DUT $end
$var parameter 2 , IDEAL $end
$var parameter 2 - MV_UP $end
$var parameter 2 . MV_DN $end
$var wire 1 / UP_Max $end
$var wire 1 0 DN_Max $end
$var wire 1 1 Activate $end
$var wire 1 2 CLK $end
$var wire 1 3 RST $end
$var reg 1 4 UP_M $end
$var reg 1 5 DN_M $end
$var reg 2 6 current_state [1:0] $end
$var reg 2 7 next_state [1:0] $end
$upscope $end
$upscope $end
$enddefinitions $end
#0
$dumpvars
0"
1#
0$
0%
1&
x4
x5
bx 6
b0 7
x)
x*
x+
b10100 !
b0 ,
b1 -
b10 .
x'
x(
13
02
01
10
0/
$end
#10000
1%
12
b0 6
04
05
0'
0(
#20000
0&
0%
03
02
#30000
1%
12
#40000
1&
1$
0%
13
11
02
b1 7
#50000
1%
12
b1 6
14
1'
#60000
1)
0*
1+
0%
02
#70000
1%
12
#80000
0%
02
#90000
1%
12
#100000
1"
0#
0$
0)
1*
0+
0%
1/
00
01
02
b0 7
#110000
1%
12
b0 6
04
0'
#120000
1$
0%
11
02
b10 7
#130000
1%
12
b10 6
15
1(
#140000
1)
0%
02
#150000
1%
12
#160000
0%
02
#170000
1%
12
#180000
0$
0"
1#
0)
0*
1+
0%
01
0/
10
02
b0 7
#190000
1%
12
b0 6
05
0(
