CRC/CRC.v
module CRC #(
    parameter width = 8, SEED  = 8'hd8) (
    input  wire Data,
    input  wire Active,
    input  wire CLK,
   	input  wire RST,
	
	output reg  valid,
    output reg  CRC
    
);

    reg [width-1:0] LFSR;
    reg [3:0]       Counter;
    wire            Feedback;

      

    assign Feedback = LFSR[0]^Data;

    always @(posedge CLK or negedge RST) begin
        if (!RST)
            begin
                LFSR  <= SEED ;
                CRC   <= 1'b0 ;
                valid <= 1'b0 ;
            end
        else
            begin
            if(Active)
               begin
	             LFSR[0]<=LFSR[1];
	             LFSR[1]<=LFSR[2];
		         LFSR[2]<=LFSR[3]^Feedback;
		         LFSR[3]<=LFSR[4];
		         LFSR[4]<=LFSR[5];
		         LFSR[5]<=LFSR[6];
		         LFSR[6]<=LFSR[7]^Feedback;
		         LFSR[7]<=Feedback;
		         valid <= 1'b0;
			
                   
               end
            else if (Counter != 4'b1000)
                begin
                  
                    {LFSR[6:0],CRC} <= LFSR;
                 
                     valid = 1'b1;
                end     
                    
    end
    end

    always @(posedge CLK or negedge RST) begin
        if(!RST)
            begin
                Counter <= 4'b1000;
            end
        else if (!Active)
            begin
                 Counter <= Counter + 4'b0001;
            end   
        else
            begin
                Counter <= 4'b0000;
            end     

    end
    
endmodule

CRC/CRC_tb.v
`timescale 1ns/1ps

module crc_tb();

parameter CRC_width  = 8 ;
parameter Test_Cases = 10 ;
parameter CLK_PERIOD = 100 ;

reg  Data_tb;
reg  Active_tb;
reg  CLK_tb;
reg  RST_tb;
wire valid_tb;
wire CRC_tb;

integer operation;

reg [CRC_width-1:0] Data_Type     [Test_Cases-1:0];
reg [CRC_width-1:0]  EXP_OUT       [Test_Cases-1:0];



initial begin
    $dumpfile("crc.vcd");
    $dumpvars;

    $readmemh("DATA_h.txt",Data_Type);
    $readmemh("Expec_Out_h.txt",EXP_OUT);

    initialize();

    for(operation=0;operation<Test_Cases;operation=operation+1)
        begin
            Reset();
            Read_OP(Data_Type[operation]);
            OUT_OP(EXP_OUT[operation],operation);
        end

        #100
        $stop;
end

task initialize(); 
    begin
       Data_tb   = 1'b0;
       Active_tb = 1'b0;
       CLK_tb    = 1'b0;
       RST_tb    = 1'b0; 
    end
endtask

task Reset();
    begin
        RST_tb = 1'b1;
        #CLK_PERIOD
        RST_tb = 1'b0;
        #CLK_PERIOD
        RST_tb = 1'b1;  
    end
endtask

task Read_OP;
input   [CRC_width-1:0] Data_in;

integer i;

    begin
        Active_tb = 1'b1;
        for(i=0;i<CRC_width;i=i+1)
            begin
                Data_tb = Data_in[i];
                #CLK_PERIOD;
            end       
        Active_tb = 1'b0;

    end
endtask

task OUT_OP ;
    input          [CRC_width-1:0] Expec_OUT;
    input integer                  oper_num;

    reg            [CRC_width-1:0] Gener_OUT;

    integer i;

        begin
            @(posedge valid_tb)
            for(i=0;i<CRC_width;i=i+1)
                begin
                    #CLK_PERIOD    Gener_OUT[i] = CRC_tb;
                end
            if (Gener_OUT == Expec_OUT)
                begin
                    $display("Test %d is Passed OUT %h and EXP OUT %h",oper_num,Gener_OUT,Expec_OUT);
                end    
            else
                begin
                    $display("Test %d is Failed OUT %h and EXP OUT %h",oper_num,Gener_OUT,Expec_OUT);
                end    
        end
endtask

always #(CLK_PERIOD/2) CLK_tb = ~CLK_tb;

CRC DUT (
    .Data(Data_tb),
    .Active(Active_tb),
    .CLK(CLK_tb),
    .RST(RST_tb),
    .valid(valid_tb),
    .CRC(CRC_tb)
);

endmodule

CRC/CRC.vcd
$date
	Thu Mar 07 02:12:52 2024
$end
$version
	ModelSim Version 10.1d
$end
$timescale
	1ps
$end
$scope module crc_tb $end
$var parameter 32 ! CRC_width $end
$var parameter 32 " Test_Cases $end
$var parameter 32 # CLK_PERIOD $end
$var reg 1 $ Data_tb $end
$var reg 1 % Active_tb $end
$var reg 1 & CLK_tb $end
$var reg 1 ' RST_tb $end
$var wire 1 ( valid_tb $end
$var wire 1 ) CRC_tb $end
$var integer 32 * operation $end
$scope task initialize $end
$upscope $end
$scope task Reset $end
$upscope $end
$scope task Read_OP $end
$var reg 8 + Data_in [7:0] $end
$var integer 32 , i $end
$upscope $end
$scope task OUT_OP $end
$var reg 8 - Expec_OUT [7:0] $end
$var integer 32 . oper_num $end
$var reg 8 / Gener_OUT [7:0] $end
$var integer 32 0 i $end
$upscope $end
$scope module DUT $end
$var parameter 32 1 width $end
$var parameter 8 2 SEED $end
$var wire 1 3 Data $end
$var wire 1 4 Active $end
$var wire 1 5 CLK $end
$var wire 1 6 RST $end
$var reg 1 7 valid $end
$var reg 1 8 CRC $end
$var reg 8 9 LFSR [7:0] $end
$var reg 4 : Counter [3:0] $end
$var wire 1 ; Feedback $end
$upscope $end
$upscope $end
$enddefinitions $end
#0
$dumpvars
0$
0%
0&
1'
bx +
bx -
bx /
x7
x8
bx 9
bx :
b1000 !
b1010 "
b1100100 #
b1000 1
b11011000 2
b0 *
bx ,
bx .
bx 0
x(
x)
x;
16
05
04
03
$end
#50000
1&
15
#100000
0'
0&
06
05
b11011000 9
08
07
b1000 :
0;
0)
0(
#150000
1&
15
#200000
1'
b10010011 +
1%
b0 ,
1$
0&
14
13
1;
16
05
#250000
1&
15
b11001000 9
b11101000 9
b10101000 9
b0 :
#300000
b1 ,
0&
05
#350000
1&
15
b10100000 9
b10110000 9
b10010000 9
#400000
b10 ,
0$
0&
03
0;
05
#450000
1&
15
b10011000 9
b10001000 9
b11001000 9
b1001000 9
#500000
b11 ,
0&
05
#550000
1&
15
b1001100 9
b1000100 9
b1100100 9
b100100 9
#600000
b100 ,
1$
0&
13
1;
05
#650000
1&
15
b100110 9
b110110 9
b10110 9
b1010110 9
b11010110 9
#700000
b101 ,
0$
0&
03
0;
05
#750000
1&
15
b11010111 9
b11010011 9
b11011011 9
b11001011 9
b11101011 9
b1101011 9
1;
#800000
b110 ,
0&
05
#850000
1&
15
b1101001 9
b1100001 9
b1110001 9
b11110001 9
#900000
b111 ,
1$
0&
13
0;
05
#950000
1&
15
b11110000 9
b11111000 9
b1111000 9
1;
#1000000
b1000 ,
0%
b1111000 -
b0 .
0&
04
05
#1050000
1&
15
17
1(
b0 0
b111100 9
b1 :
#1100000
0&
05
#1150000
bx0 /
b1 0
1&
15
b11110 9
b10 :
#1200000
0&
05
#1250000
bx00 /
b10 0
1&
15
b1111 9
b11 :
0;
#1300000
0&
05
#1350000
bx000 /
b11 0
1&
15
18
b111 9
b100 :
1)
#1400000
0&
05
#1450000
bx1000 /
b100 0
1&
15
b11 9
b101 :
#1500000
0&
05
#1550000
bx11000 /
b101 0
1&
15
b1 9
b110 :
#1600000
0&
05
#1650000
bx111000 /
b110 0
1&
15
b0 9
b111 :
1;
#1700000
0&
05
#1750000
bx1111000 /
b111 0
1&
15
08
b1000 :
0)
#1800000
0&
05
#1850000
b1111000 /
b1000 0
b1 *
1&
15
b1001 :
#1900000
0&
05
#1950000
0'
1&
06
15
b11011000 9
07
b1000 :
0(
#2000000
0&
05
#2050000
1'
b1110010 +
1%
b0 ,
0$
1&
14
03
0;
16
15
b11011100 9
b11001100 9
b11101100 9
b1101100 9
b0 :
#2100000
0&
05
#2150000
b1 ,
1$
1&
13
1;
15
b1101110 9
b1101010 9
b1100010 9
b1110010 9
b11110010 9
#2200000
0&
05
#2250000
b10 ,
0$
1&
03
0;
15
b11110011 9
b11110001 9
b11111001 9
b1111001 9
1;
#2300000
0&
05
#2350000
b11 ,
1&
15
b1111000 9
b11111000 9
0;
#2400000
0&
05
#2450000
b100 ,
1$
1&
13
1;
15
b10111000 9
#2500000
0&
05
#2550000
b101 ,
1&
15
b10011000 9
#2600000
0&
05
#2650000
b110 ,
1&
15
b10001000 9
#2700000
0&
05
#2750000
b111 ,
0$
1&
03
0;
15
b10001100 9
b10000100 9
b11000100 9
b1000100 9
#2800000
0&
05
#2850000
b1000 ,
0%
b1000100 -
b1 .
1&
04
15
17
1(
b0 0
b100010 9
b1 :
#2900000
0&
05
#2950000
b1 0
1&
15
b10001 9
b10 :
1;
#3000000
0&
05
#3050000
b10 0
1&
15
18
b1000 9
b11 :
1)
0;
#3100000
0&
05
#3150000
b1111100 /
b11 0
1&
15
08
b100 9
b100 :
0)
#3200000
0&
05
#3250000
b1110100 /
b100 0
1&
15
b10 9
b101 :
#3300000
0&
05
#3350000
b1100100 /
b101 0
1&
15
b1 9
b110 :
1;
#3400000
0&
05
#3450000
b1000100 /
b110 0
1&
15
18
b0 9
b111 :
1)
0;
#3500000
0&
05
#3550000
b111 0
1&
15
08
b1000 :
0)
#3600000
0&
05
#3650000
b1000 0
b10 *
1&
15
b1001 :
#3700000
0&
05
#3750000
0'
1&
06
15
b11011000 9
07
b1000 :
0(
#3800000
0&
05
#3850000
1'
b110110 +
1%
b0 ,
1&
14
16
15
b11011100 9
b11001100 9
b11101100 9
b1101100 9
b0 :
#3900000
0&
05
#3950000
b1 ,
1$
1&
13
1;
15
b1101110 9
b1101010 9
b1100010 9
b1110010 9
b11110010 9
#4000000
0&
05
#4050000
b10 ,
1&
15
b11110011 9
b11110001 9
b11110101 9
b11111101 9
b10111101 9
0;
#4100000
0&
05
#4150000
b11 ,
0$
1&
03
1;
15
b10111100 9
b10111110 9
b10111010 9
b10011010 9
0;
#4200000
0&
05
#4250000
b100 ,
1$
1&
13
1;
15
b10011011 9
b10011001 9
b10001001 9
0;
#4300000
0&
05
#4350000
b101 ,
1&
15
b10001000 9
b10001100 9
b10000100 9
b11000100 9
b1000100 9
1;
#4400000
0&
05
#4450000
b110 ,
0$
1&
03
0;
15
b1000110 9
b1000010 9
b1100010 9
b100010 9
#4500000
0&
05
#4550000
b111 ,
1&
15
b100011 9
b100001 9
b110001 9
b10001 9
1;
#4600000
0&
05
#4650000
b1000 ,
0%
b10001 -
b10 .
1&
04
15
17
1(
b0 0
18
b1000 9
b1 :
1)
0;
#4700000
0&
05
#4750000
b1000101 /
b1 0
1&
15
08
b100 9
b10 :
0)
#4800000
0&
05
#4850000
b10 0
1&
15
b10 9
b11 :
#4900000
0&
05
#4950000
b1000001 /
b11 0
1&
15
b1 9
b100 :
1;
#5000000
0&
05
#5050000
b100 0
1&
15
18
b0 9
b101 :
1)
0;
#5100000
0&
05
#5150000
b1010001 /
b101 0
1&
15
08
b110 :
0)
#5200000
0&
05
#5250000
b110 0
1&
15
b111 :
#5300000
0&
05
#5350000
b10001 /
b111 0
1&
15
b1000 :
#5400000
0&
05
#5450000
b1000 0
b11 *
1&
15
b1001 :
#5500000
0&
05
#5550000
0'
1&
06
15
b11011000 9
07
b1000 :
0(
#5600000
0&
05
#5650000
1'
b11011 +
1%
b0 ,
1$
1&
14
13
1;
16
15
b11001000 9
b11101000 9
b10101000 9
b0 :
#5700000
0&
05
#5750000
b1 ,
1&
15
b10100000 9
b10110000 9
b10010000 9
#5800000
0&
05
#5850000
b10 ,
0$
1&
03
0;
15
b10011000 9
b10001000 9
b11001000 9
b1001000 9
#5900000
0&
05
#5950000
b11 ,
1$
1&
13
1;
15
b1000000 9
b1100000 9
b11100000 9
#6000000
0&
05
#6050000
b100 ,
1&
15
b11100100 9
b11110100 9
b10110100 9
#6100000
0&
05
#6150000
b101 ,
0$
1&
03
0;
15
b10110110 9
b10110010 9
b10111010 9
b10011010 9
b11011010 9
b1011010 9
#6200000
0&
05
#6250000
b110 ,
1&
15
b1011011 9
b1011001 9
b1011101 9
b1001101 9
b1101101 9
b101101 9
1;
#6300000
0&
05
#6350000
b111 ,
1&
15
b101100 9
b101110 9
b101010 9
b100010 9
b110010 9
b10010 9
b1010010 9
b11010010 9
0;
#6400000
0&
05
#6450000
b1000 ,
0%
b11010010 -
b11 .
1&
04
15
17
1(
b0 0
b11101001 9
b1 :
1;
#6500000
0&
05
#6550000
b10000 /
b1 0
1&
15
18
b11110100 9
b10 :
1)
0;
#6600000
0&
05
#6650000
b10010 /
b10 0
1&
15
08
b11111010 9
b11 :
0)
#6700000
0&
05
#6750000
b11 0
1&
15
b11111101 9
b100 :
1;
#6800000
0&
05
#6850000
b100 0
1&
15
18
b11111110 9
b101 :
1)
0;
#6900000
0&
05
#6950000
b101 0
1&
15
08
b11111111 9
b110 :
0)
1;
#7000000
0&
05
#7050000
b110 0
1&
15
18
b111 :
1)
#7100000
0&
05
#7150000
b1010010 /
b111 0
1&
15
b1000 :
#7200000
0&
05
#7250000
b11010010 /
b1000 0
b100 *
1&
15
b1001 :
#7300000
0&
05
#7350000
0'
1&
06
15
b11011000 9
08
07
b1000 :
0;
0)
0(
#7400000
0&
05
#7450000
1'
b10100110 +
1%
b0 ,
1&
14
16
15
b11011100 9
b11001100 9
b11101100 9
b1101100 9
b0 :
#7500000
0&
05
#7550000
b1 ,
1$
1&
13
1;
15
b1101110 9
b1101010 9
b1100010 9
b1110010 9
b11110010 9
#7600000
0&
05
#7650000
b10 ,
1&
15
b11110011 9
b11110001 9
b11110101 9
b11111101 9
b10111101 9
0;
#7700000
0&
05
#7750000
b11 ,
0$
1&
03
1;
15
b10111100 9
b10111110 9
b10111010 9
b10011010 9
0;
#7800000
0&
05
#7850000
b100 ,
1&
15
b10011011 9
b10011001 9
b10011101 9
b10001101 9
b11001101 9
b1001101 9
1;
#7900000
0&
05
#7950000
b101 ,
1$
1&
13
0;
15
b1001100 9
b1001110 9
b1000110 9
b1100110 9
b100110 9
1;
#8000000
0&
05
#8050000
b110 ,
0$
1&
03
0;
15
b100111 9
b100011 9
b110011 9
b10011 9
1;
#8100000
0&
05
#8150000
b111 ,
1$
1&
13
0;
15
b10001 9
b11001 9
b1001 9
#8200000
0&
05
#8250000
b1000 ,
0%
b1001 -
b100 .
1&
04
15
17
1(
b0 0
18
b100 9
b1 :
1)
1;
#8300000
0&
05
#8350000
b11010011 /
b1 0
1&
15
08
b10 9
b10 :
0)
#8400000
0&
05
#8450000
b11010001 /
b10 0
1&
15
b1 9
b11 :
0;
#8500000
0&
05
#8550000
b11 0
1&
15
18
b0 9
b100 :
1)
1;
#8600000
0&
05
#8650000
b11011001 /
b100 0
1&
15
08
b101 :
0)
#8700000
0&
05
#8750000
b11001001 /
b101 0
1&
15
b110 :
#8800000
0&
05
#8850000
b110 0
1&
15
b111 :
#8900000
0&
05
#8950000
b10001001 /
b111 0
1&
15
b1000 :
#9000000
0&
05
#9050000
b1001 /
b1000 0
b101 *
1&
15
b1001 :
#9100000
0&
05
#9150000
0'
1&
06
15
b11011000 9
07
b1000 :
0(
#9200000
0&
05
#9250000
1'
b11000000 +
1%
b0 ,
0$
1&
14
03
0;
16
15
b11011100 9
b11001100 9
b11101100 9
b1101100 9
b0 :
#9300000
0&
05
#9350000
b1 ,
1&
15
b1101110 9
b1100110 9
b1110110 9
b110110 9
#9400000
0&
05
#9450000
b10 ,
1&
15
b110111 9
b110011 9
b111011 9
b11011 9
1;
#9500000
0&
05
#9550000
b11 ,
1&
15
b11001 9
b1001 9
b1001001 9
b11001001 9
#9600000
0&
05
#9650000
b100 ,
1&
15
b11001000 9
b11000000 9
b11100000 9
b10100000 9
0;
#9700000
0&
05
#9750000
b101 ,
1&
15
b10110000 9
b10010000 9
b11010000 9
b1010000 9
#9800000
0&
05
#9850000
b110 ,
1$
1&
13
1;
15
b1010100 9
b1011100 9
b1001100 9
b1101100 9
b11101100 9
#9900000
0&
05
#9950000
b111 ,
1&
15
b11101110 9
b11101010 9
b11100010 9
b11110010 9
b10110010 9
#10000000
0&
05
#10050000
b1000 ,
0%
b10110010 -
b101 .
1&
04
15
17
1(
b0 0
b11011001 9
b1 :
0;
#10100000
0&
05
#10150000
b1000 /
b1 0
1&
15
18
b11101100 9
b10 :
1)
1;
#10200000
0&
05
#10250000
b1010 /
b10 0
1&
15
08
b11110110 9
b11 :
0)
#10300000
0&
05
#10350000
b11 0
1&
15
b11111011 9
b100 :
0;
#10400000
0&
05
#10450000
b10 /
b100 0
1&
15
18
b11111101 9
b101 :
1)
#10500000
0&
05
#10550000
b10010 /
b101 0
1&
15
b11111110 9
b110 :
1;
#10600000
0&
05
#10650000
b110010 /
b110 0
1&
15
08
b11111111 9
b111 :
0)
0;
#10700000
0&
05
#10750000
b111 0
1&
15
18
b1000 :
1)
#10800000
0&
05
#10850000
b10110010 /
b1000 0
b110 *
1&
15
b1001 :
#10900000
0&
05
#10950000
0'
1&
06
15
b11011000 9
08
07
b1000 :
1;
0)
0(
#11000000
0&
05
#11050000
1'
b1010101 +
1%
b0 ,
1&
14
16
15
b11001000 9
b11101000 9
b10101000 9
b0 :
#11100000
0&
05
#11150000
b1 ,
0$
1&
03
0;
15
b10101100 9
b10100100 9
b10110100 9
b10010100 9
b11010100 9
b1010100 9
#11200000
0&
05
#11250000
b10 ,
1$
1&
13
1;
15
b1010110 9
b1011110 9
b1001110 9
b1101110 9
b11101110 9
#11300000
0&
05
#11350000
b11 ,
0$
1&
03
0;
15
b11101111 9
b11100111 9
b11110111 9
b1110111 9
1;
#11400000
0&
05
#11450000
b100 ,
1$
1&
13
0;
15
b1110011 9
b1111011 9
b111011 9
#11500000
0&
05
#11550000
b101 ,
0$
1&
03
1;
15
b111001 9
b11001 9
b1011001 9
b11011001 9
#11600000
0&
05
#11650000
b110 ,
1$
1&
13
0;
15
b11011000 9
b11011100 9
b11001100 9
b11101100 9
b1101100 9
1;
#11700000
0&
05
#11750000
b111 ,
0$
1&
03
0;
15
b1101110 9
b1100110 9
b1110110 9
b110110 9
#11800000
0&
05
#11850000
b1000 ,
0%
b110110 -
b110 .
1&
04
15
17
1(
b0 0
b11011 9
b1 :
1;
#11900000
0&
05
#11950000
b1 0
1&
15
18
b1101 9
b10 :
1)
#12000000
0&
05
#12050000
b10 0
1&
15
b110 9
b11 :
0;
#12100000
0&
05
#12150000
b10110110 /
b11 0
1&
15
08
b11 9
b100 :
0)
1;
#12200000
0&
05
#12250000
b100 0
1&
15
18
b1 9
b101 :
1)
#12300000
0&
05
#12350000
b101 0
1&
15
b0 9
b110 :
0;
#12400000
0&
05
#12450000
b110 0
1&
15
08
b111 :
0)
#12500000
0&
05
#12550000
b111 0
1&
15
b1000 :
#12600000
0&
05
#12650000
b110110 /
b1000 0
b111 *
1&
15
b1001 :
#12700000
0&
05
#12750000
0'
1&
06
15
b11011000 9
07
b1000 :
0(
#12800000
0&
05
#12850000
1'
b11110010 +
1%
b0 ,
1&
14
16
15
b11011100 9
b11001100 9
b11101100 9
b1101100 9
b0 :
#12900000
0&
05
#12950000
b1 ,
1$
1&
13
1;
15
b1101110 9
b1101010 9
b1100010 9
b1110010 9
b11110010 9
#13000000
0&
05
#13050000
b10 ,
0$
1&
03
0;
15
b11110011 9
b11110001 9
b11111001 9
b1111001 9
1;
#13100000
0&
05
#13150000
b11 ,
1&
15
b1111000 9
b11111000 9
0;
#13200000
0&
05
#13250000
b100 ,
1$
1&
13
1;
15
b10111000 9
#13300000
0&
05
#13350000
b101 ,
1&
15
b10011000 9
#13400000
0&
05
#13450000
b110 ,
1&
15
b10001000 9
#13500000
0&
05
#13550000
b111 ,
1&
15
b10000000 9
#13600000
0&
05
#13650000
b1000 ,
0%
b10000000 -
b111 .
1&
04
15
17
1(
b0 0
b11000000 9
b1 :
#13700000
0&
05
#13750000
b1 0
1&
15
b11100000 9
b10 :
#13800000
0&
05
#13850000
b110100 /
b10 0
1&
15
b11110000 9
b11 :
#13900000
0&
05
#13950000
b110000 /
b11 0
1&
15
b11111000 9
b100 :
#14000000
0&
05
#14050000
b100 0
1&
15
b11111100 9
b101 :
#14100000
0&
05
#14150000
b100000 /
b101 0
1&
15
b11111110 9
b110 :
#14200000
0&
05
#14250000
b0 /
b110 0
1&
15
b11111111 9
b111 :
0;
#14300000
0&
05
#14350000
b111 0
1&
15
18
b1000 :
1)
#14400000
0&
05
#14450000
b10000000 /
b1000 0
b1000 *
1&
15
b1001 :
#14500000
0&
05
#14550000
0'
1&
06
15
b11011000 9
08
07
b1000 :
1;
0)
0(
#14600000
0&
05
#14650000
1'
b1011110 +
1%
b0 ,
0$
1&
14
03
0;
16
15
b11011100 9
b11001100 9
b11101100 9
b1101100 9
b0 :
#14700000
0&
05
#14750000
b1 ,
1$
1&
13
1;
15
b1101110 9
b1101010 9
b1100010 9
b1110010 9
b11110010 9
#14800000
0&
05
#14850000
b10 ,
1&
15
b11110011 9
b11110001 9
b11110101 9
b11111101 9
b10111101 9
0;
#14900000
0&
05
#14950000
b11 ,
1&
15
b10111100 9
b10111110 9
b10011110 9
b11011110 9
b1011110 9
1;
#15000000
0&
05
#15050000
b100 ,
1&
15
b1011111 9
b1011011 9
b1001011 9
b1101011 9
b11101011 9
0;
#15100000
0&
05
#15150000
b101 ,
0$
1&
03
1;
15
b11101001 9
b11100001 9
b11110001 9
b10110001 9
#15200000
0&
05
#15250000
b110 ,
1$
1&
13
0;
15
b10110000 9
b10111000 9
b10011000 9
b11011000 9
b1011000 9
1;
#15300000
0&
05
#15350000
b111 ,
0$
1&
03
0;
15
b1011100 9
b1001100 9
b1101100 9
b101100 9
#15400000
0&
05
#15450000
b1000 ,
0%
b101100 -
b1000 .
1&
04
15
17
1(
b0 0
b10110 9
b1 :
#15500000
0&
05
#15550000
b1 0
1&
15
b1011 9
b10 :
1;
#15600000
0&
05
#15650000
b10 0
1&
15
18
b101 9
b11 :
1)
#15700000
0&
05
#15750000
b10000100 /
b11 0
1&
15
b10 9
b100 :
0;
#15800000
0&
05
#15850000
b10001100 /
b100 0
1&
15
08
b1 9
b101 :
0)
1;
#15900000
0&
05
#15950000
b101 0
1&
15
18
b0 9
b110 :
1)
0;
#16000000
0&
05
#16050000
b10101100 /
b110 0
1&
15
08
b111 :
0)
#16100000
0&
05
#16150000
b111 0
1&
15
b1000 :
#16200000
0&
05
#16250000
b101100 /
b1000 0
b1001 *
1&
15
b1001 :
#16300000
0&
05
#16350000
0'
1&
06
15
b11011000 9
07
b1000 :
0(
#16400000
0&
05
#16450000
1'
b10001 +
1%
b0 ,
1$
1&
14
13
1;
16
15
b11001000 9
b11101000 9
b10101000 9
b0 :
#16500000
0&
05
#16550000
b1 ,
0$
1&
03
0;
15
b10101100 9
b10100100 9
b10110100 9
b10010100 9
b11010100 9
b1010100 9
#16600000
0&
05
#16650000
b10 ,
1&
15
b1010110 9
b1010010 9
b1011010 9
b1001010 9
b1101010 9
b101010 9
#16700000
0&
05
#16750000
b11 ,
1&
15
b101011 9
b101001 9
b101101 9
b100101 9
b110101 9
b10101 9
1;
#16800000
0&
05
#16850000
b100 ,
1$
1&
13
0;
15
b10100 9
b10110 9
b10010 9
b11010 9
b1010 9
1;
#16900000
0&
05
#16950000
b101 ,
0$
1&
03
0;
15
b1011 9
b1001 9
b1101 9
b101 9
1;
#17000000
0&
05
#17050000
b110 ,
1&
15
b100 9
b110 9
b1000110 9
b11000110 9
0;
#17100000
0&
05
#17150000
b111 ,
1&
15
b11000111 9
b11000011 9
b11100011 9
b1100011 9
1;
#17200000
0&
05
#17250000
b1000 ,
0%
b1100011 -
b1001 .
1&
04
15
17
1(
b0 0
18
b110001 9
b1 :
1)
#17300000
0&
05
#17350000
b101101 /
b1 0
1&
15
b11000 9
b10 :
0;
#17400000
0&
05
#17450000
b101111 /
b10 0
1&
15
08
b1100 9
b11 :
0)
#17500000
0&
05
#17550000
b101011 /
b11 0
1&
15
b110 9
b100 :
#17600000
0&
05
#17650000
b100011 /
b100 0
1&
15
b11 9
b101 :
1;
#17700000
0&
05
#17750000
b101 0
1&
15
18
b1 9
b110 :
1)
#17800000
0&
05
#17850000
b110 0
1&
15
b0 9
b111 :
0;
#17900000
0&
05
#17950000
b1100011 /
b111 0
1&
15
08
b1000 :
0)
#18000000
0&
05
#18050000
b1000 0
b1010 *
1&
15
b1001 :
